baobaxia/__init__.py
baobaxia/acervo.py
baobaxia/client.py
baobaxia/install.py
baobaxia/rest.py
baobaxia/root.py
baobaxia/saberes.py
baobaxia/sankofa.py
baobaxia/util.py
baobaxia-0.1.24.dist-info/LICENSE
baobaxia-0.1.24.dist-info/METADATA
baobaxia-0.1.24.dist-info/WHEEL
baobaxia-0.1.24.dist-info/entry_points.txt
baobaxia-0.1.24.dist-info/top_level.txt
baobaxia-0.1.24.dist-info/RECORD
