Metadata-Version: 2.1
Name: baobaxia
Version: 0.1.24
Summary: Baobáxia is an eventually connected data network
Home-page: https://labmocambos.taina.net.br/npdd/baobaxia-mucua
Author: NPDD/Rede Mocambos
Author-email: npdd@mocambos.net
License: UNKNOWN
Platform: UNKNOWN
Classifier: Development Status :: 3 - Alpha
Classifier: Programming Language :: Python :: 3
Classifier: License :: OSI Approved :: GNU General Public License v3 (GPLv3)
Classifier: Operating System :: OS Independent
Requires-Dist: aiofiles
Requires-Dist: datalad
Requires-Dist: fastapi
Requires-Dist: pydantic[dotenv,email]
Requires-Dist: pygments
Requires-Dist: python-multipart
Requires-Dist: python-slugify
Requires-Dist: shortuuid
Requires-Dist: starlette
Requires-Dist: uvicorn[standard]
